{
  "project_info": {
    "project_number": "342614079428",
    "project_id": "smartservices-notif",
    "storage_bucket": "smartservices-notif.firebasestorage.app"
  },
  "client": [
    {
      "client_info": {
        "mobilesdk_app_id": "1:342614079428:android:4bb2d9c3cc125b803f5691",
        "android_client_info": {
          "package_name": "com.example.mobile_app"
        }
      },
      "oauth_client": [],
      "api_key": [
        {
          "current_key": "AIzaSyD6IoYXNhrTWZ3lIKnpdQRqwhs3AsYBjkM"
        }
      ],
      "services": {
        "appinvite_service": {
          "other_platform_oauth_client": []
        }
      }
    }
  ],
  "configuration_version": "1"
}